{
 "id": "food_FOOD00336",
 "name": "Coconut (food medium)",
 "food_record": "https://foodb.ca/foods/FOOD00336",
 "foodb_url": "https://foodb.ca/foods",
 "current_components": [
  "Nonanoate",
  "L-Alanine",
  "L-Arginine",
  "L-Ascorbate",
  "Arsenate",
  "L-Aspartate",
  "Alpha-Tocopherol",
  "Biotin",
  "Calcium",
  "Cadmium",
  "Choline C5H14NO",
  "Chloride",
  "CO2 CO2",
  "Co2+",
  "Copper",
  "L-cystine",
  "Decanoic acid",
  "Dodecanoic acid",
  "Fe2+ mitochondria",
  "Iron (Fe3+)",
  "Iron",
  "Folate",
  "D-Fructose",
  "Galactomannan C6H10O5",
  "D-Glucose",
  "L-Glutamate",
  "Glycine",
  "Glycine betaine",
  "Gamma-Tocopherol",
  "H2O H2O",
  "H+",
  "L-Histidine",
  "Heptanoate",
  "Hexanoate (n-C6:0)",
  "L-Isoleucine",
  "Myo-Inositol",
  "Iodine c",
  "Potassium",
  "L-Leucine",
  "L-Lysine",
  "L-Methionine",
  "Magnesium",
  "Manganese",
  "Molybdate",
  "Nitrogen",
  "Sodium",
  "Nicotinate",
  "Ammonium",
  "Nickel",
  "O2 O2",
  "Pentadecanoic acid",
  "Phosphate",
  "L-Proline",
  "Pyridoxine",
  "Raffinose C18H32O16",
  "Sulfur",
  "D-Serine",
  "Sulfate",
  "Sucrose C12H22O11",
  "L-Threonine",
  "L-Tryptophan",
  "L-Tyrosine",
  "Zinc",
  "Selenium",
  "Chromium",
  "C18:1, n-9",
  "(Z,Z)-9,12-Octadecadienoic acid",
  "Pantothenic acid",
  "Thiamine",
  "Riboflavine",
  "Phytomenadione",
  "Octanoic acid",
  "Lead",
  "Mercury"
 ],
 "current_uncovered": [
  "Methoxyl",
  "(E)-2-Phenyl-2-butenal",
  "(\u00b1)-erythro-Isoleucine",
  "Calcium oxide",
  "epsilon-Polylysine",
  "(R)-Oxypeucedanin",
  "Silicon",
  "Rubidium",
  "Aluminum",
  "Titanium",
  "Boron",
  "Bromine",
  "Strontium",
  "Fluorine",
  "Tin",
  "Tungsten",
  "Isoflavones",
  "Antimony",
  "Barium",
  "Cesium",
  "Europium",
  "Ytterbium",
  "Genistein",
  "Samarium",
  "Lanthanum",
  "Lutetium",
  "Vanadium",
  "Scandium"
 ],
 "n_current": 74
}